dataflake/cache/__init__.py
dataflake/cache/interfaces.py
dataflake/cache/simple.py
dataflake/cache/timeout.py
dataflake/cache/utils.py
dataflake/cache/tests/__init__.py
dataflake/cache/tests/base.py
dataflake/cache/tests/test_docs.py
dataflake/cache/tests/test_simple.py
dataflake/cache/tests/test_timeout.py
dataflake_cache-3.3.dist-info/licenses/LICENSE.txt
dataflake_cache-3.3.dist-info/METADATA
dataflake_cache-3.3.dist-info/WHEEL
dataflake_cache-3.3.dist-info/top_level.txt
dataflake_cache-3.3.dist-info/RECORD
